Workbook

Sheet Cover Page
B2: TEST AUTOMATION ESTIMATE
B3: ATS — Oracle Recruiting Cloud (ORC) · Option B: extend the existing automation framework
B5: PROJECT DETAILS
B6: Project Name | C6: Oracle Recruiting Cloud (ORC) Implementation
B7: Client / Org | C7: Cognizant
B8: Estimate For | C8: Automation of the ATS ORC SIT/UAT regression suite
B9: Test Lead | C9: Tejal Dalavi
B10: Delivery Approach | C10: Extend the existing Selenium 4.40 + Cucumber 7.33 + TestNG + Allure framework
B11: Framework Source | C11: github.com/Vishnu-vardhan-401/erp-hcm-regression-testing
B12: Scope Source | C12: ATS_ORC_Test_Script_Register_20AUG26.xlsx (Fit/Gap V1.1)
B13: Estimation Model | C13: HGV_Automation Estimation_Uipath_V1.0.xlsx (activity structure)
B14: Version | C14: 1.0
B15: Prepared By | C15: Vishnu Vardhan G
B16: Date | C16: 24-Aug-2026
B17: Status | C17: Draft for review
B19: ESTIMATE AT A GLANCE
B20: Can the ATS ORC suite be automated? | C20: Yes — see breakdown below
B21: Total test scripts in register | C21: =Scope!$D$6 -> 152 | D21: scripts
B22: In scope for automation | C22: =Scope!$D$7 -> 144 | D22: scripts
B23: Recommended to stay manual | C23: =Scope!$D$8 -> 8 | D23: scripts
B24: Complexity mix (Simple / Medium / Complex) | C24: =Scope!$D$12&" / "&Scope!$E$12&" / "&Scope!$F$12 -> 34 / 89 / 21 | D24: scripts
B25: Total automation effort | C25: ='Overall Estimation'!$D$25 -> 1105.468 | D25: hours
B26: Total effort in person days | C26: ='Overall Estimation'!$D$27 -> 138.1835 | D26: person days
B27: Recommended team | C27: Scenario A — 3 automation engineers + test manager + ORC SME
B28: Indicative duration | C28: ='Resourcing Scenarios'!$G$16 -> 9.2122333 | D28: weeks
B29: Indicative duration (months) | C29: ='Resourcing Scenarios'!$H$16 -> 2.3030583 | D29: months
B30: Fastest option (Scenario C) | C30: ='Resourcing Scenarios'!$G$18 -> 4.3867778 | D30: weeks with 7 engineers
B31: Effort saved vs UiPath option | C31: ='Tool Comparison'!$D$14 -> 0.27507443 | D31: lower effort
B33: WORKBOOK CONTENTS
B34: Scope | C34: Script volumes, complexity mix, coverage by module, banding basis, and the scripts excluded from automation.
B35: Complexity Basis | C35: All 152 scripts with step count, personas, complexity score and band, in-scope flag and the drivers behind each rating.
B36: Framework Reuse | C36: What the existing framework already provides, what must be built, and the sizing of the ORC component library.
B37: Overall Estimation | C37: The effort model — KT, framework uplift, component library, scripting, dry run, PM and contingency, with a contingency sensitivity.
B38: Resourcing Scenarios | C38: Three team sizes and the duration each produces, with squad composition.
B39: Resourcing Model | C39: Phase plan by week and resource ramp by month for the recommended scenario.
B40: Tool Comparison | C40: UiPath Test Suite vs extending the existing framework — effort, duration, cost and risk side by side.
B41: Assumptions & Risks | C41: Basis of estimate, assumptions, exclusions and risks with mitigations.
B43: CELL LEGEND
B44: Input / assumption | C44: Blue bold text on a yellow fill — editable lever. Change these to flex the estimate.
B45: Calculated | C45: Black text — driven by formulas. Do not overwrite.

Sheet Scope
B2: AUTOMATION SCOPE — ATS Oracle Recruiting Cloud (ORC)
B3: Derived from ATS_ORC_Test_Script_Register_20AUG26.xlsx (152 scripts, Fit/Gap V1.1). Scope is identical to the UiPath estimate — only the delivery approach differs.
B5: SCRIPT VOLUMES
C6: Total Test Scripts in Register | D6: =COUNTA('Complexity Basis'!$B$2:$B$153) -> 152 | E6: % of total
C7: In Scope for Automation | D7: =COUNTIF('Complexity Basis'!$M$2:$M$153,"Yes") -> 144 | E7: =D7/$D$6 -> 0.94736842
C8: Excluded — to remain manual | D8: =COUNTIF('Complexity Basis'!$M$2:$M$153,"No") -> 8 | E8: =D8/$D$6 -> 0.052631579
B10: AUTOMATION TEST SUITE — SCOPE BY COMPLEXITY
C11: Complexity | D11: Simple | E11: Medium | F11: Complex | G11: Total | H11: Feeds the "Overall Estimation" tab.
C12: Number of Test Scripts | D12: =COUNTIFS('Complexity Basis'!$L$2:$L$153,"Simple",'Complexity Basis'!$M$2:$M$153,"Yes") -> 34 | E12: =COUNTIFS('Complexity Basis'!$L$2:$L$153,"Medium",'Complexity Basis'!$M$2:$M$153,"Yes") -> 89 | F12: =COUNTIFS('Complexity Basis'!$L$2:$L$153,"Complex",'Complexity Basis'!$M$2:$M$153,"Yes") -> 21 | G12: =SUM(D12:F12) -> 144
C13: % Mix | D13: =D12/$G$12 -> 0.23611111 | E13: =E12/$G$12 -> 0.61805556 | F13: =F12/$G$12 -> 0.14583333 | G13: =SUM(D13:F13) -> 1
B15: SCOPE BY MODULE (PROCESS)
C16: Module (Process) | D16: Total Scripts | E16: In Scope | F16: Simple | G16: Medium | H16: Complex | I16: Excluded
C17: Job Requisition | D17: =COUNTIF('Complexity Basis'!$D$2:$D$153,"Job Requisition") -> 32 | E17: =COUNTIFS('Complexity Basis'!$D$2:$D$153,"Job Requisition",'Complexity Basis'!$M$2:$M$153,"Yes") -> 30 | F17: =COUNTIFS('Complexity Basis'!$D$2:$D$153,"Job Requisition",'Complexity Basis'!$L$2:$L$153,"Simple",'Complexity Basis'!$M$2:$M$153,"Yes") -> 10 | G17: =COUNTIFS('Complexity Basis'!$D$2:$D$153,"Job Requisition",'Complexity Basis'!$L$2:$L$153,"Medium",'Complexity Basis'!$M$2:$M$153,"Yes") -> 18 | H17: =COUNTIFS('Complexity Basis'!$D$2:$D$153,"Job Requisition",'Complexity Basis'!$L$2:$L$153,"Complex",'Complexity Basis'!$M$2:$M$153,"Yes") -> 2 | I17: =COUNTIFS('Complexity Basis'!$D$2:$D$153,"Job Requisition",'Complexity Basis'!$M$2:$M$153,"No") -> 2
C18: Job Offer | D18: =COUNTIF('Complexity Basis'!$D$2:$D$153,"Job Offer") -> 26 | E18: =COUNTIFS('Complexity Basis'!$D$2:$D$153,"Job Offer",'Complexity Basis'!$M$2:$M$153,"Yes") -> 26 | F18: =COUNTIFS('Complexity Basis'!$D$2:$D$153,"Job Offer",'Complexity Basis'!$L$2:$L$153,"Simple",'Complexity Basis'!$M$2:$M$153,"Yes") -> 3 | G18: =COUNTIFS('Complexity Basis'!$D$2:$D$153,"Job Offer",'Complexity Basis'!$L$2:$L$153,"Medium",'Complexity Basis'!$M$2:$M$153,"Yes") -> 18 | H18: =COUNTIFS('Complexity Basis'!$D$2:$D$153,"Job Offer",'Complexity Basis'!$L$2:$L$153,"Complex",'Complexity Basis'!$M$2:$M$153,"Yes") -> 5 | I18: =COUNTIFS('Complexity Basis'!$D$2:$D$153,"Job Offer",'Complexity Basis'!$M$2:$M$153,"No") -> 0
C19: Candidate Selection Process | D19: =COUNTIF('Complexity Basis'!$D$2:$D$153,"Candidate Selection Process") -> 25 | E19: =COUNTIFS('Complexity Basis'!$D$2:$D$153,"Candidate Selection Process",'Complexity Basis'!$M$2:$M$153,"Yes") -> 25 | F19: =COUNTIFS('Complexity Basis'!$D$2:$D$153,"Candidate Selection Process",'Complexity Basis'!$L$2:$L$153,"Simple",'Complexity Basis'!$M$2:$M$153,"Yes") -> 3 | G19: =COUNTIFS('Complexity Basis'!$D$2:$D$153,"Candidate Selection Process",'Complexity Basis'!$L$2:$L$153,"Medium",'Complexity Basis'!$M$2:$M$153,"Yes") -> 18 | H19: =COUNTIFS('Complexity Basis'!$D$2:$D$153,"Candidate Selection Process",'Complexity Basis'!$L$2:$L$153,"Complex",'Complexity Basis'!$M$2:$M$153,"Yes") -> 4 | I19: =COUNTIFS('Complexity Basis'!$D$2:$D$153,"Candidate Selection Process",'Complexity Basis'!$M$2:$M$153,"No") -> 0
C20: Employee Referral | D20: =COUNTIF('Complexity Basis'!$D$2:$D$153,"Employee Referral") -> 21 | E20: =COUNTIFS('Complexity Basis'!$D$2:$D$153,"Employee Referral",'Complexity Basis'!$M$2:$M$153,"Yes") -> 21 | F20: =COUNTIFS('Complexity Basis'!$D$2:$D$153,"Employee Referral",'Complexity Basis'!$L$2:$L$153,"Simple",'Complexity Basis'!$M$2:$M$153,"Yes") -> 8 | G20: =COUNTIFS('Complexity Basis'!$D$2:$D$153,"Employee Referral",'Complexity Basis'!$L$2:$L$153,"Medium",'Complexity Basis'!$M$2:$M$153,"Yes") -> 13 | H20: =COUNTIFS('Complexity Basis'!$D$2:$D$153,"Employee Referral",'Complexity Basis'!$L$2:$L$153,"Complex",'Complexity Basis'!$M$2:$M$153,"Yes") -> 0 | I20: =COUNTIFS('Complexity Basis'!$D$2:$D$153,"Employee Referral",'Complexity Basis'!$M$2:$M$153,"No") -> 0
C21: Candidate Experience | D21: =COUNTIF('Complexity Basis'!$D$2:$D$153,"Candidate Experience") -> 13 | E21: =COUNTIFS('Complexity Basis'!$D$2:$D$153,"Candidate Experience",'Complexity Basis'!$M$2:$M$153,"Yes") -> 12 | F21: =COUNTIFS('Complexity Basis'!$D$2:$D$153,"Candidate Experience",'Complexity Basis'!$L$2:$L$153,"Simple",'Complexity Basis'!$M$2:$M$153,"Yes") -> 1 | G21: =COUNTIFS('Complexity Basis'!$D$2:$D$153,"Candidate Experience",'Complexity Basis'!$L$2:$L$153,"Medium",'Complexity Basis'!$M$2:$M$153,"Yes") -> 10 | H21: =COUNTIFS('Complexity Basis'!$D$2:$D$153,"Candidate Experience",'Complexity Basis'!$L$2:$L$153,"Complex",'Complexity Basis'!$M$2:$M$153,"Yes") -> 1 | I21: =COUNTIFS('Complexity Basis'!$D$2:$D$153,"Candidate Experience",'Complexity Basis'!$M$2:$M$153,"No") -> 1
C22: Security | D22: =COUNTIF('Complexity Basis'!$D$2:$D$153,"Security") -> 9 | E22: =COUNTIFS('Complexity Basis'!$D$2:$D$153,"Security",'Complexity Basis'!$M$2:$M$153,"Yes") -> 9 | F22: =COUNTIFS('Complexity Basis'!$D$2:$D$153,"Security",'Complexity Basis'!$L$2:$L$153,"Simple",'Complexity Basis'!$M$2:$M$153,"Yes") -> 6 | G22: =COUNTIFS('Complexity Basis'!$D$2:$D$153,"Security",'Complexity Basis'!$L$2:$L$153,"Medium",'Complexity Basis'!$M$2:$M$153,"Yes") -> 3 | H22: =COUNTIFS('Complexity Basis'!$D$2:$D$153,"Security",'Complexity Basis'!$L$2:$L$153,"Complex",'Complexity Basis'!$M$2:$M$153,"Yes") -> 0 | I22: =COUNTIFS('Complexity Basis'!$D$2:$D$153,"Security",'Complexity Basis'!$M$2:$M$153,"No") -> 0
C23: Integration | D23: =COUNTIF('Complexity Basis'!$D$2:$D$153,"Integration") -> 9 | E23: =COUNTIFS('Complexity Basis'!$D$2:$D$153,"Integration",'Complexity Basis'!$M$2:$M$153,"Yes") -> 9 | F23: =COUNTIFS('Complexity Basis'!$D$2:$D$153,"Integration",'Complexity Basis'!$L$2:$L$153,"Simple",'Complexity Basis'!$M$2:$M$153,"Yes") -> 2 | G23: =COUNTIFS('Complexity Basis'!$D$2:$D$153,"Integration",'Complexity Basis'!$L$2:$L$153,"Medium",'Complexity Basis'!$M$2:$M$153,"Yes") -> 1 | H23: =COUNTIFS('Complexity Basis'!$D$2:$D$153,"Integration",'Complexity Basis'!$L$2:$L$153,"Complex",'Complexity Basis'!$M$2:$M$153,"Yes") -> 6 | I23: =COUNTIFS('Complexity Basis'!$D$2:$D$153,"Integration",'Complexity Basis'!$M$2:$M$153,"No") -> 0
C24: Interview Management | D24: =COUNTIF('Complexity Basis'!$D$2:$D$153,"Interview Management") -> 9 | E24: =COUNTIFS('Complexity Basis'!$D$2:$D$153,"Interview Management",'Complexity Basis'!$M$2:$M$153,"Yes") -> 9 | F24: =COUNTIFS('Complexity Basis'!$D$2:$D$153,"Interview Management",'Complexity Basis'!$L$2:$L$153,"Simple",'Complexity Basis'!$M$2:$M$153,"Yes") -> 0 | G24: =COUNTIFS('Complexity Basis'!$D$2:$D$153,"Interview Management",'Complexity Basis'!$L$2:$L$153,"Medium",'Complexity Basis'!$M$2:$M$153,"Yes") -> 6 | H24: =COUNTIFS('Complexity Basis'!$D$2:$D$153,"Interview Management",'Complexity Basis'!$L$2:$L$153,"Complex",'Complexity Basis'!$M$2:$M$153,"Yes") -> 3 | I24: =COUNTIFS('Complexity Basis'!$D$2:$D$153,"Interview Management",'Complexity Basis'!$M$2:$M$153,"No") -> 0
C25: AI Agents | D25: =COUNTIF('Complexity Basis'!$D$2:$D$153,"AI Agents") -> 3 | E25: =COUNTIFS('Complexity Basis'!$D$2:$D$153,"AI Agents",'Complexity Basis'!$M$2:$M$153,"Yes") -> 0 | F25: =COUNTIFS('Complexity Basis'!$D$2:$D$153,"AI Agents",'Complexity Basis'!$L$2:$L$153,"Simple",'Complexity Basis'!$M$2:$M$153,"Yes") -> 0 | G25: =COUNTIFS('Complexity Basis'!$D$2:$D$153,"AI Agents",'Complexity Basis'!$L$2:$L$153,"Medium",'Complexity Basis'!$M$2:$M$153,"Yes") -> 0 | H25: =COUNTIFS('Complexity Basis'!$D$2:$D$153,"AI Agents",'Complexity Basis'!$L$2:$L$153,"Complex",'Complexity Basis'!$M$2:$M$153,"Yes") -> 0 | I25: =COUNTIFS('Complexity Basis'!$D$2:$D$153,"AI Agents",'Complexity Basis'!$M$2:$M$153,"No") -> 3
C26: Reporting & Analytics | D26: =COUNTIF('Complexity Basis'!$D$2:$D$153,"Reporting & Analytics") -> 3 | E26: =COUNTIFS('Complexity Basis'!$D$2:$D$153,"Reporting & Analytics",'Complexity Basis'!$M$2:$M$153,"Yes") -> 3 | F26: =COUNTIFS('Complexity Basis'!$D$2:$D$153,"Reporting & Analytics",'Complexity Basis'!$L$2:$L$153,"Simple",'Complexity Basis'!$M$2:$M$153,"Yes") -> 1 | G26: =COUNTIFS('Complexity Basis'!$D$2:$D$153,"Reporting & Analytics",'Complexity Basis'!$L$2:$L$153,"Medium",'Complexity Basis'!$M$2:$M$153,"Yes") -> 2 | H26: =COUNTIFS('Complexity Basis'!$D$2:$D$153,"Reporting & Analytics",'Complexity Basis'!$L$2:$L$153,"Complex",'Complexity Basis'!$M$2:$M$153,"Yes") -> 0 | I26: =COUNTIFS('Complexity Basis'!$D$2:$D$153,"Reporting & Analytics",'Complexity Basis'!$M$2:$M$153,"No") -> 0
C27: Recruiting Booster | D27: =COUNTIF('Complexity Basis'!$D$2:$D$153,"Recruiting Booster") -> 2 | E27: =COUNTIFS('Complexity Basis'!$D$2:$D$153,"Recruiting Booster",'Complexity Basis'!$M$2:$M$153,"Yes") -> 0 | F27: =COUNTIFS('Complexity Basis'!$D$2:$D$153,"Recruiting Booster",'Complexity Basis'!$L$2:$L$153,"Simple",'Complexity Basis'!$M$2:$M$153,"Yes") -> 0 | G27: =COUNTIFS('Complexity Basis'!$D$2:$D$153,"Recruiting Booster",'Complexity Basis'!$L$2:$L$153,"Medium",'Complexity Basis'!$M$2:$M$153,"Yes") -> 0 | H27: =COUNTIFS('Complexity Basis'!$D$2:$D$153,"Recruiting Booster",'Complexity Basis'!$L$2:$L$153,"Complex",'Complexity Basis'!$M$2:$M$153,"Yes") -> 0 | I27: =COUNTIFS('Complexity Basis'!$D$2:$D$153,"Recruiting Booster",'Complexity Basis'!$M$2:$M$153,"No") -> 2
C28: Total | D28: =SUM(D17:D27) -> 152 | E28: =SUM(E17:E27) -> 144 | F28: =SUM(F17:F27) -> 34 | G28: =SUM(G17:G27) -> 89 | H28: =SUM(H17:H27) -> 21 | I28: =SUM(I17:I27) -> 8
B30: COMPLEXITY BANDING BASIS (applied script-by-script on "Complexity Basis")
C31: Scoring drivers (+) | D31: Test steps: 8–11 = +1, 12+ = +2 • Persona/login handoffs: 2 = +1, 3+ = +2 • Third-party integration (Talview, Mercer, PeopleSoft, background check, e-storage) = +3 • AI / non-deterministic output = +3 • Approval workflow = +1 • Email / notification / SMS = +1 • OTBI or report validation = +1 • Career-site / external candidate UI = +1 • File, resume or document handling = +1 • Bulk or mass action = +1
C32: Scoring drivers (−) | D32: Pure configuration or field-visibility assertion (suppress / hidden / read-only / restricted / label) = −1
C33: Band thresholds | D33: Score ≤ 1 = Simple • Score 2–4 = Medium • Score ≥ 5 = Complex
C34: Why this matters | D34: The band drives both scripting and dry-run productivity rates on the "Overall Estimation" tab.
B36: SCRIPTS EXCLUDED FROM AUTOMATION — recommended to remain manual
C37: Test Script ID | D37: Module | E37: Sub-Process | F37: Reason for Exclusion
C38: TC01-JR | D38: Job Requisition | E38: AI Recruiting Assistant / Chatbot | F38: AI-generated output is non-deterministic — no stable expected result to assert against. Validate manually / by sampling.
C39: TC018-JR | D39: Job Requisition | E39: Agency Posting Approval | F39: Classified GAP in Fit/Gap V1.1 — only an interim manual workaround exists; no configured ORC behaviour to automate.
C40: TC012-CE | D40: Candidate Experience | E40: AI Agent Reuse | F40: AI-generated output is non-deterministic — no stable expected result to assert against. Validate manually / by sampling.
C41: TC01-AI | D41: AI Agents | E41: AI Referral Matching | F41: Classified GAP in Fit/Gap V1.1 — only an interim manual workaround exists; no configured ORC behaviour to automate.
C42: TC01-RB | D42: Recruiting Booster | E42: Targeted Campaigns | F42: Delivery is via an external channel (SMS / campaign platform) outside the ORC UI — no automatable assertion point.
C43: TC02-RB | D43: Recruiting Booster | E43: SMS Communication | F43: Classified GAP in Fit/Gap V1.1 — only an interim manual workaround exists; no configured ORC behaviour to automate.
C44: TC02-AI | D44: AI Agents | E44: Voice AI Agents | F44: AI-generated output is non-deterministic — no stable expected result to assert against. Validate manually / by sampling.
C45: TC03-AI | D45: AI Agents | E45: AI in Candidate Selection Process | F45: AI-generated output is non-deterministic — no stable expected result to assert against. Validate manually / by sampling.
C47: Excluded scripts carry no automation build effort. They remain in the manual SIT/UAT pack.

Sheet Complexity Basis
A1: S.No | B1: Test Script ID | C1: Req ID | D1: Module (Process) | E1: Sub-Process | F1: Priority | G1: Classification | H1: Test Type | I1: No. of Test Steps | J1: Personas Involved | K1: Complexity Score | L1: Complexity Band | M1: In Scope for Automation | N1: Automation Viability / Reason | O1: Complexity Drivers
A2: 1 | B2: TC01-REF | C2: REQ_ERP_0001 | D2: Employee Referral | E2: Referral UI Configuration | F2: Medium | G2: FIT | H2: Positive | I2: 6 | J2: 3 | K2: 1 | L2: Simple | M2: Yes | N2: Automate | O2: 6 steps; 3 personas/2 logins; config/visibility assertion
A3: 2 | B3: TC02-REF | C3: REQ_ERP_0002 | D3: Employee Referral | E3: Referral Notifications | F3: Low | G3: FIT | H3: Positive | I3: 5 | J3: 3 | K3: 3 | L3: Medium | M3: Yes | N3: Automate | O3: 5 steps; 3 personas/1 logins; email/notification
A4: 3 | B4: TC03-REF | C4: REQ_ERP_0003 | D4: Employee Referral | E4: Job Search Configuration | F4: Medium | G4: FIT | H4: Positive | I4: 5 | J4: 2 | K4: 2 | L4: Medium | M4: Yes | N4: Automate | O4: 5 steps; 2 personas/1 logins; career-site/external UI
A5: 4 | B5: TC04-REF | C5: REQ_ERP_0003 | D5: Employee Referral | E5: Job Search Configuration | F5: Medium | G5: FIT | H5: Negative | I5: 6 | J5: 1 | K5: -1 | L5: Simple | M5: Yes | N5: Automate | O5: 6 steps; config/visibility assertion
A6: 5 | B6: TC05-REF | C6: REQ_ERP_0004 | D6: Employee Referral | E6: Referral Configuration Governance | F6: Medium | G6: FIT | H6: Positive | I6: 5 | J6: 2 | K6: 3 | L6: Medium | M6: Yes | N6: Automate | O6: 5 steps; 2 personas/1 logins; email/notification; career-site/external UI
A7: 6 | B7: TC06-REF | C7: REQ_ERP_0005 | D7: Employee Referral | E7: Duplicate Management | F7: High | G7: FIT | H7: Positive | I7: 10 | J7: 2 | K7: 4 | L7: Medium | M7: Yes | N7: Automate | O7: 10 steps; 2 personas/1 logins; email/notification; file/doc handling
A8: 7 | B8: TC07-REF | C8: REQ_ERP_0005 | D8: Employee Referral | E8: Duplicate Management | F8: High | G8: FIT | H8: Negative | I8: 8 | J8: 1 | K8: 2 | L8: Medium | M8: Yes | N8: Automate | O8: 8 steps; email/notification
A9: 8 | B9: TC08-REF | C9: REQ_ERP_0006 | D9: Employee Referral | E9: Resume Parsing (Referral Portal) | F9: Medium | G9: PARTIAL FIT | H9: Positive | I9: 10 | J9: 1 | K9: 2 | L9: Medium | M9: Yes | N9: Automate | O9: 10 steps; file/doc handling
A10: 9 | B10: TC09-REF | C10: REQ_ERP_0006 | D10: Employee Referral | E10: Resume Parsing (Referral Portal) | F10: Medium | G10: PARTIAL FIT | H10: Negative | I10: 8 | J10: 1 | K10: 2 | L10: Medium | M10: Yes | N10: Automate | O10: 8 steps; file/doc handling
A11: 10 | B11: TC010-REF | C11: REQ_ERP_0007 | D11: Employee Referral | E11: Referral Form Configuration | F11: Low | G11: FIT | H11: Positive | I11: 10 | J11: 1 | K11: 0 | L11: Simple | M11: Yes | N11: Automate | O11: 10 steps; config/visibility assertion
A12: 11 | B12: TC011-REF | C12: REQ_ERP_0008 | D12: Employee Referral | E12: Referral Consent Capture | F12: High | G12: FIT | H12: Positive | I12: 10 | J12: 1 | K12: 2 | L12: Medium | M12: Yes | N12: Automate | O12: 10 steps; email/notification
A13: 12 | B13: TC012-REF | C13: REQ_ERP_0008 | D13: Employee Referral | E13: Referral Consent Capture | F13: High | G13: FIT | H13: Negative | I13: 10 | J13: 1 | K13: 2 | L13: Medium | M13: Yes | N13: Automate | O13: 10 steps; email/notification
... A153: 152 | B153: TC025-CSP | C153: REQ_CSP_0020 | D153: Candidate Selection Process | E153: Rehire Employee ID Capture / Flow | F153: High | G153: FIT | H153: Positive | I153: 9 | J153: 2 | K153: 5 | L153: Complex | M153: Yes | N153: Automate | O153: 9 steps; 2 personas/1 logins; email/notification; report/OTBI; career-site/external UI

Sheet Framework Reuse
B2: EXISTING FRAMEWORK — what carries over to ORC, and what must be built
B3: Source: github.com/Vishnu-vardhan-401/erp-hcm-regression-testing. This tab is the evidence behind the lower environment set-up and script-development effort in this estimate.
B5: ASSETS ALREADY BUILT (reused for ORC)
B6: Asset | C6: What it does | D6: Size | E6: Reuse for ORC
B7: Selenium + Cucumber + TestNG + Allure stack | C7: Selenium 4.40, Cucumber 7.33, TestNG, Allure 2.29, Apache POI — already on a current, supported toolchain. | D7: pom.xml | E7: Direct
B8: Wrapper.java | C8: 30+ reusable interaction methods: waits, JS click, scroll, highlight, Oracle date picker, custom oj- dropdown select, screenshot capture, Allure pass/fail reporting. | D8: 454 lines | E8: Direct
B9: redwoodSync() | C9: Redwood/JET page-settle helper already in place — the Redwood UI is a solved problem in this framework, not a new risk. | D9: In Wrapper | E9: Direct (harden)
B10: HCMCoreHR.java | C10: Mature Oracle Fusion page object — 685 locators, overwhelmingly Redwood/JET component-based (oj-select-single ×111, oj-input-text, oj-input-date, oj-switch, oj-table, oj-list-view). | D10: 9,055 lines | E10: Pattern + locator strategy
B11: HCMSecurity.java + TileValidationReportUtil | C11: Generic role/tile visibility validator driven from Excel, with HTML result tables in Allure. | D11: 682 + 295 lines | E11: Direct — maps to the 9 ORC Security scripts
B12: ExcelReader + Excel-driven runner | C12: Key-based Excel lookup plus ExcelDrivenCucumberRunner / ExcelFeaturePicker — test selection and data both driven from a spreadsheet the test team can edit. | D12: 95 + 420 lines | E12: Direct
B13: AllureReportUtil + Hooks | C13: Screenshot-on-failure, text/HTML/CSV/PNG attachments, scenario tagging and context. | D13: 83 + 39 lines | E13: Direct
B14: Delivered scenarios | C14: 56 Core HR + 27 Security scenarios already automated and reported against an Oracle Fusion pod. | D14: 83 scenarios | E14: Proof of throughput
B15: Total framework code in repo | C15: Across page objects, step definitions, utilities, hooks and runners. | D15: 13,314 lines
B17: GAPS TO CLOSE (this is what the "Framework Uplift & Environment Set-up" line pays for)
B18: Gap | C18: Why it matters for ORC | D18: Fix
B19: Single static WebDriver in BaseClass | C19: No parallel execution. With 144 scripts and multi-persona flows, serial runs make every regression cycle long. | D19: Refactor to a ThreadLocal driver.
B20: driver.quit() after every scenario (Hooks) | C20: A fresh browser and a fresh Oracle login per scenario — the slowest part of each run. | D20: Session reuse per persona where the test allows.
B21: redwoodSync() uses a fixed 4-second sleep | C21: A hard 4s wait on every call inflates runtime across 144 scripts. | D21: Replace with a condition-based wait.
B22: Hardcoded Windows chromedriver paths | C22: Will not run on a Linux CI agent. | D22: Selenium Manager / WebDriverManager.
B23: No ORC/Recruitment page objects | C23: PageObjectManagerHCM has the Recruitment page object commented out — ORC screens do not exist yet. | D23: Covered by the component library build below.
B24: testng.xml is a stub; no CI pipeline in repo | C24: No scheduled or triggered execution. | D24: Suite definition plus a CI job.
B26: COMPONENT / PAGE OBJECT LIBRARY BUILD
B27: Hours per new component | D27: 7 | E27: Locator discovery on Redwood/JET, page-object methods and stabilisation. Single biggest lever on this tab.
C29: Functional Area | D29: Components Required | E29: Reuse from Existing Framework | F29: Net New Components | G29: Hours
C30: Common / shared (login, navigation, search, dropdowns, dates, upload, notifications, approvals) | D30: 8 | E30: 0.85 | F30: =D30*(1-E30) -> 1.2 | G30: =F30*$D$27 -> 8.4
C31: Job Requisition (create/edit, posting, prescreening, activity centre, approvals, status) | D31: 7 | E31: 0.1 | F31: =D31*(1-E31) -> 6.3 | G31: =F31*$D$27 -> 44.1
C32: Job Offer (offer create, fields, compensation, approvals, letter & documents, phases) | D32: 7 | E32: 0.1 | F32: =D32*(1-E32) -> 6.3 | G32: =F32*$D$27 -> 44.1
C33: Candidate Selection Process (search, profile, disposition, duplicate check, sources, bulk) | D33: 6 | E33: 0.1 | F33: =D33*(1-E33) -> 5.4 | G33: =F33*$D$27 -> 37.8
C34: Employee Referral portal (referral form, job search, dashboard, consent, notifications) | D34: 5 | E34: 0.1 | F34: =D34*(1-E34) -> 4.5 | G34: =F34*$D$27 -> 31.5
C35: Candidate Experience / career site (easy apply, talent community, question sets, branding) | D35: 5 | E35: 0.05 | F35: =D35*(1-E35) -> 4.75 | G35: =F35*$D$27 -> 33.25
C36: Interview Management (scheduling, feedback templates, panel, surveys) | D36: 4 | E36: 0.1 | F36: =D36*(1-E36) -> 3.6 | G36: =F36*$D$27 -> 25.2
C37: Security (role / tile visibility) | D37: 3 | E37: 0.8 | F37: =D37*(1-E37) -> 0.6 | G37: =F37*$D$27 -> 4.2
C38: Reporting & Analytics (OTBI) | D38: 2 | E38: 0.25 | F38: =D38*(1-E38) -> 1.5 | G38: =F38*$D$27 -> 10.5
C39: Integration boundary / stubs | D39: 3 | E39: 0.1 | F39: =D39*(1-E39) -> 2.7 | G39: =F39*$D$27 -> 18.9
C40: Total | D40: =SUM(D30:D39) -> 50 | F40: =SUM(F30:F39) -> 36.85 | G40: =SUM(G30:G39) -> 257.95
B42: Reuse % basis: | C42: Common and Security are high because Wrapper, BaseClass, ExcelReader, AllureReportUtil, HCMSecurity and TileValidationReportUtil already deliver that behaviour against Oracle Fusion. The ORC transaction screens (requisition, candidate, offer, referral portal, career site) do not exist in the framework and are costed as new, with a small credit for shared UI patterns.

Sheet Overall Estimation
A2: TEST AUTOMATION ESTIMATION — ATS Oracle Recruiting Cloud (ORC)
A3: Approach: extend the existing Selenium 4.40 + Cucumber + TestNG + Allure framework | Scope identical to the UiPath estimate | Blue/shaded cells are inputs.
A5: Effort Splitup
B6: Automation Activities | C6: Activity Description | D6: Estimated Hours (Phase I) | E6: Complexity | F6: No. of Scripts | G6: Rate | H6: Basis
B7: KT / Automation Planning | C7: Identification and knowledge transfer of the ORC test scripts to the automation team; walkthrough of Fit/Gap V1.1 and the recruiting business processes. Tool-independent — unchanged from the UiPath estimate. | D7: =H10 -> 22.916667 | E7: Simple | F7: =Scope!D12 -> 34 | G7: 5 | H7: =F7*G7/60 -> 2.8333333 | I7: Minutes per script
E8: Medium | F8: =Scope!E12 -> 89 | G8: 10 | H8: =F8*G8/60 -> 14.833333
E9: Complex | F9: =Scope!F12 -> 21 | G9: 15 | H9: =F9*G9/60 -> 5.25
F10: =SUM(F7:F9) -> 144 | G10: Total in hrs | H10: =SUM(H7:H9) -> 22.916667
B11: Framework Uplift & Environment Set-up | C11: ThreadLocal driver refactor for parallel execution, session reuse in Hooks, condition-based redwoodSync, Selenium Manager for cross-platform drivers, ORC pod configuration and test-user wiring, TestNG suite definition and CI pipeline. No tool licensing or install — the framework already exists. | D11: 32 | E11: =CONCATENATE(D11/8," Days") -> 4 Days | I11: vs 56 hrs on UiPath
B12: Component / Page Object Library Build | C12: One-time build of the ORC page objects and reusable components, net of what the existing framework already provides. Sized area by area on the "Framework Reuse" tab. | D12: ='Framework Reuse'!$G$40 -> 257.95 | E12: From "Framework Reuse"
B13: Automation Script Development | C13: 1. Prepare Automation Test Plan 2. Write feature files and step definitions per test script 3. Prepare test data template(s) Rates assume the component library above is in place, so scripting is assembly of existing page-object methods. | D13: =G17+I17 -> 544.55873 | E13: Simple | F13: Medium | G13: Complex
E14: =ROUND(1/E15,2) -> 0.29 | F14: =ROUND(1/F15,2) -> 0.44 | G14: =ROUND(1/G15,2) -> 0.8 | H14: Days per script
E15: 3.5 | F15: 2.25 | G15: 1.25 | H15: No. of scripts / day
E16: =$F$7/E15*8 -> 77.714286 | F16: =$F$8/F15*8 -> 316.44444 | G16: =$F$9/G15*8 -> 134.4 | H16: Hours
F17: Total in hrs | G17: =SUM(E16:G16) -> 528.55873 | H17: Test Plan & Data Templates (hrs) | I17: 16
B18: Automation Execution (Dry Run) | C18: 1. Prepare test data and populate the Excel test data template(s) 2. Dry-run execution, defect triage and script stabilisation. Rates assume parallel execution is available after the framework uplift. | D18: =G22 -> 145.26667 | E18: Simple | F18: Medium | G18: Complex
E19: =ROUND(1/E20,2) -> 0.08 | F19: =ROUND(1/F20,2) -> 0.13 | G19: =ROUND(1/G20,2) -> 0.2 | H19: Days per script
E20: 12 | F20: 8 | G20: 5 | H20: No. of scripts / day
E21: =$F$7/E20*8 -> 22.666667 | F21: =$F$8/F20*8 -> 89 | G21: =$F$9/G20*8 -> 33.6 | H21: Hours
F22: Total in hrs | G22: =SUM(E21:G21) -> 145.26667
B23: Project Management | C23: Automation test management, planning, status reporting, governance and stakeholder co-ordination. | D23: =SUM(D7:D22)*E23 -> 50.134603 | E23: 0.05 | F23: of build effort
B24: Contingency | C24: Contingency for environment non-availability, ORC quarterly update impact and rework. Held at 5% for comparability — see the sensitivity block below. | D24: =SUM(D7:D23)*E24 -> 52.641333 | E24: 0.05 | F24: of effort incl. PM
C25: Overall Effort (Hours) | D25: =SUM(D7:D24) -> 1105.468
C27: Total Person Days | D27: =D25/8 -> 138.1835 | E27: 1 person day = 8 hrs
C28: Total Person Weeks | D28: =D27/5 -> 27.6367 | E28: 1 person week = 5 days
C29: Total Person Months | D29: =D28/4 -> 6.909175 | E29: 1 month = 4 weeks (per source model)
C30: Estimated Resources (Automation Engineers) | D30: 3 | E30: Flex this cell, or see "Resourcing Scenarios"
C31: Duration (in Weeks) | D31: =D28/D30 -> 9.2122333 | E31: =D31/4 -> 2.3030583 | F31: Months
B33: CONTINGENCY SENSITIVITY
C34: Contingency % | D34: Overall Effort (Hours) | E34: Person Weeks | F34: Duration @ 3 engineers (weeks)
C35: 0.05 | D35: =(SUM($D$7:$D$22)+SUM($D$7:$D$22)*$E$23)*(1+C35) -> 1105.468 | E35: =D35/8/5 -> 27.6367 | F35: =E35/$D$30 -> 9.2122333 | G35: Comparable with the UiPath estimate.
C36: 0.08 | D36: =(SUM($D$7:$D$22)+SUM($D$7:$D$22)*$E$23)*(1+C36) -> 1137.0528 | E36: =D36/8/5 -> 28.42632 | F36: =E36/$D$30 -> 9.47544 | G36: Reflects a code-based framework carrying its own locator maintenance.
C37: 0.12 | D37: =(SUM($D$7:$D$22)+SUM($D$7:$D$22)*$E$23)*(1+C37) -> 1179.1659 | E37: =D37/8/5 -> 29.479147 | F37: =E37/$D$30 -> 9.8263822 | G37: Prudent if ORC configuration is still moving during the build.

Sheet Resourcing Scenarios
B2: RESOURCING SCENARIOS — effort is fixed, only elapsed time changes
B3: Total effort from the "Overall Estimation" tab is constant across all three scenarios. Adding engineers compresses the calendar but costs more in co-ordination, which the efficiency factor reflects.
B5: SQUAD COMPOSITION
B6: Role | C6: Scenario A Lean | D6: Scenario B Balanced | E6: Scenario C Accelerated | F6: Counts as automation engineer?
B7: Automation Test Manager | C7: 0.5 | D7: 1 | E7: 1 | F7: No
B8: Senior Automation Tester (Java/Selenium) | C8: 1 | D8: 2 | E8: 2 | F8: Yes
B9: Automation Tester (Java/Selenium) | C9: 2 | D9: 3 | E9: 5 | F9: Yes
B10: Functional SME / BA (ORC) | C10: 1 | D10: 1 | E10: 2 | F10: No
B11: Automation Engineers (build capacity) | C11: =SUM(C8:C9) -> 3 | D11: =SUM(D8:D9) -> 5 | E11: =SUM(E8:E9) -> 7 | F11: Senior + Testers
B12: Total Squad Size | C12: =SUM(C7:C10) -> 4.5 | D12: =SUM(D7:D10) -> 7 | E12: =SUM(E7:E10) -> 10
B14: DURATION BY SCENARIO
B15: Scenario | C15: Automation Engineers | D15: Team Efficiency Factor | E15: Effective Capacity (FTE) | F15: Computed Duration (Weeks) | G15: Planned Duration (Weeks) | H15: Planned Duration (Months) | I15: Guidance
B16: A — Lean (Recommended) | C16: =C11 -> 3 | D16: 1 | E16: =C16*D16 -> 3 | F16: ='Overall Estimation'!$D$28/E16 -> 9.2122333 | G16: =MAX(F16,$C$22) -> 9.2122333 | H16: =G16/4 -> 2.3030583 | I16: Mirrors the 3-engineer default. The component library is the critical path — one senior engineer owning it keeps the page objects consistent.
B17: B — Balanced | C17: =D11 -> 5 | D17: 0.95 | E17: =C17*D17 -> 4.75 | F17: ='Overall Estimation'!$D$28/E17 -> 5.8182526 | G17: =MAX(F17,$C$22) -> 5.8182526 | H17: =G17/4 -> 1.4545632 | I17: Use when the SIT/UAT window is tight. Split the component library by module across two seniors, with a shared locator convention agreed up front.
B18: C — Accelerated | C18: =E11 -> 7 | D18: 0.9 | E18: =C18*D18 -> 6.3 | F18: ='Overall Estimation'!$D$28/E18 -> 4.3867778 | G18: =MAX(F18,$C$22) -> 4.3867778 | H18: =G18/4 -> 1.0966944 | I18: Only viable if the component library is complete before the extra testers join — five people writing page objects in parallel will duplicate locators.
B20: Total effort (person weeks) — constant | C20: ='Overall Estimation'!$D$28 -> 27.6367 | D20: Effort does not fall as the team grows; only elapsed time does.
B22: Serial floor (weeks) | C22: 3.5 | D22: Framework uplift, KT and final sign-off cannot be parallelised. Lower than the UiPath floor because no tool install or Orchestrator setup is needed.

Sheet Resourcing Model
B2: DELIVERY TIMELINE — Scenario A (Lean: 3 automation engineers, ~10 weeks)
B3: Indicative phasing. Weeks are relative to automation kick-off, not calendar dates.
B5: PHASE PLAN
B6: Phase | C6: W1 | D6: W2 | E6: W3 | F6: W4 | G6: W5 | H6: W6 | I6: W7 | J6: W8 | K6: W9 | L6: W10
B7: Analyse manual test suite & KT on ORC business processes
B8: Framework uplift (ThreadLocal, Selenium Manager, CI, ORC config)
B9: Build ORC component / page object library
B10: Write feature files & step definitions
B11: Dry run of automation scripts
B12: Defect triage & script stabilisation
B13: Suite sign-off & user guide
B16: RESOURCE RAMP (headcount by month, 1 month = 4 weeks)
B17: Role | C17: Month 1 | D17: Month 2 | E17: Month 3
B18: Automation Test Manager | C18: 0.5 | D18: 0.5 | E18: 0.5
B19: Senior Automation Tester (Java/Selenium) | C19: 1 | D19: 1 | E19: 1
B20: Automation Tester (Java/Selenium) | C20: 1 | D20: 2 | E20: 2
B21: Functional SME / BA (ORC) | C21: 1 | D21: 1 | E21: 0.5
B22: Total | C22: =SUM(C18:C21) -> 3.5 | D22: =SUM(D18:D21) -> 4.5 | E22: =SUM(E18:E21) -> 4
B24: Note: the senior engineer owns the component library end to end so locator conventions stay consistent. The Functional SME steps down once script design is signed off.

Sheet Tool Comparison
B2: TOOL COMPARISON — UiPath Test Suite vs extending the existing framework
B3: UiPath figures are carried across from ATS_ORC_Automation_Estimation_UiPath_V1.0.xlsx and are entered as constants (blue). Selenium figures are live formulas from this workbook. Both cover the same 144 in-scope scripts.
B5: QUANTITATIVE
B6: Measure | C6: UiPath Test Suite | D6: Extend Existing Framework | E6: Difference
B7: Overall effort (hours) | C7: 1524.94 | D7: ='Overall Estimation'!$D$25 -> 1105.468 | E7: =D7-C7 -> -419.472
B8: Total person days | C8: 190.62 | D8: ='Overall Estimation'!$D$27 -> 138.1835 | E8: =D8-C8 -> -52.4365
B9: Total person weeks | C9: 38.12 | D9: ='Overall Estimation'!$D$28 -> 27.6367 | E9: =D9-C9 -> -10.4833
B10: Environment / framework set-up (hours) | C10: 56 | D10: ='Overall Estimation'!$D$11 -> 32 | E10: =D10-C10 -> -24
B11: Duration @ 3 engineers (weeks) | C11: 12.71 | D11: ='Resourcing Scenarios'!$G$16 -> 9.2122333 | E11: =D11-C11 -> -3.4977667
B12: Duration @ 5 engineers (weeks) | C12: 8.03 | D12: ='Resourcing Scenarios'!$G$17 -> 5.8182526 | E12: =D12-C12 -> -2.2117474
B13: Effort per in-scope script (hours) | C13: =C7/Scope!$D$7 -> 10.589861 | D13: =D7/Scope!$D$7 -> 7.6768611 | E13: =D13-C13 -> -2.913
B14: Saving vs UiPath | D14: =1-D7/C7 -> 0.27507443 | E14: lower effort
B16: QUALITATIVE
B17: Dimension | C17: UiPath Test Suite | D17: Extend Existing Framework
B18: Tool licence cost | C18: Per-seat Studio and Test Manager plus Orchestrator. Not costed in either estimate — add it here. | D18: Nil. Open-source stack already in use.
B19: Reusable assets on day 1 | C19: None specific to ORC. Object repository built from scratch. | D19: 13,314 lines of framework code, 685 Redwood-aware locators, 30+ wrapper methods, Excel data layer, Allure reporting.
B20: Proven on Oracle Fusion? | C20: Vendor-supported, but unproven in this team. | D20: Yes — 83 scenarios already delivered against an Oracle Fusion pod.
B21: Redwood / JET handling | C21: Vendor-maintained Oracle selectors. | D21: redwoodSync() plus oj-component locator strategy already proven on Core HR.
B22: Skills required | C22: UiPath Studio. Lower barrier, easier to staff from outside the team. | D22: Java, Selenium, Cucumber. The team already has this; harder to backfill.
B23: Parallel execution | C23: Orchestrator, out of the box. | D23: Needs the ThreadLocal refactor — included in the 32-hour uplift.
B24: CI/CD | C24: Orchestrator scheduling and dashboards. | D24: Maven + TestNG on any standard CI. Pipeline not yet in the repo.
B25: Maintenance model | C25: Vendor absorbs some UI change; licence renews annually. | D25: Team owns every locator. Cheaper to run, but the burden is real and needs funding.
B26: Vendor support | C26: Yes, with SLAs. | D26: Community only.
B27: Principal risk | C27: Licence cost and lock-in; a second asset base to maintain alongside the existing one. | D27: Maintenance capacity. If the team that owns the framework moves on, the suite decays.
B29: Read this as: | C29: Extending the framework is cheaper and faster because the hard part — a Redwood-aware Oracle Fusion automation layer — already exists and is proven. The trade is that all maintenance sits with your team. UiPath buys vendor support and easier staffing, at licence cost and with no reuse of what is already built.

Sheet Assumptions & Risks
B2: ASSUMPTIONS, EXCLUSIONS & RISKS
B4: BASIS OF ESTIMATE
C5: Scope source | D5: ATS_ORC_Test_Script_Register_20AUG26.xlsx — 152 test scripts derived from ATS - ORC - Fit/Gap V1.1, prepared by Tejal Dalavi, 17-Aug-2026.
C6: Estimation model | D6: Activity structure from HGV_Automation Estimation_Uipath_V1.0.xlsx, with the build split into a one-time component library plus per-script scripting — the accurate shape for a code-based framework.
C7: Delivery approach | D7: Extend the existing Selenium 4.40 + Cucumber 7.33 + TestNG + Allure framework (github.com/Vishnu-vardhan-401/erp-hcm-regression-testing).
C8: What changed from the UiPath estimate | D8: Environment set-up 56 → 32 hrs, a separately sized component library net of existing reuse, and faster per-script rates once page objects exist. KT, scope and complexity banding are unchanged.
B10: ASSUMPTIONS
B11: 1 | C11: The existing framework repository is available to the ORC team, and the engineers who built it are available for handover.
B12: 2 | C12: A working ORC test instance is available for the full duration, with stable configuration and no mid-build re-implementation of recruiting flows.
B13: 3 | C13: Test users are provisioned up front for every persona in the register — Recruiter, Hiring Manager, Employee/Referrer, Candidate, Interviewer, Agency and Administrator — with passwords that do not expire during the engagement.
B14: 4 | C14: The 152 scripts are baselined before automation begins. The register itself notes that test steps, preconditions, test data and expected results are still to be edited and reviewed.
B15: 5 | C15: Component-library rates assume the page objects follow the existing convention (contains(@id, ...) on oj- components) rather than positional XPath.
B16: 6 | C16: Per-script rates assume the relevant page objects exist before scripting starts for that module — hence the phase overlap on the "Resourcing Model" tab.
B17: 7 | C17: Engineers are already skilled in Java, Selenium and Cucumber. No tool training is included.
B18: 8 | C18: One person day = 8 hours, one person week = 5 days, one month = 4 weeks.
B19: 9 | C19: Effort covers build and dry run only (Phase I). Regression execution cycles after handover are estimated separately.
B20: 10 | C20: Third-party integration scripts (Talview, Mercer Belong, PeopleSoft, background check, e-storage) are automated against stubs or a vendor sandbox; if neither is available these 9 scripts move to manual.
B22: EXCLUSIONS
B23: 1 | C23: Performance, load, security-penetration and accessibility testing.
B24: 2 | C24: Manual SIT/UAT execution effort, and the 8 scripts listed as excluded on the "Scope" tab.
B25: 3 | C25: Infrastructure, CI runner and browser-grid hosting costs.
B26: 4 | C26: Test management tool licences and configuration.
B27: 5 | C27: Post-handover regression execution and maintenance for Oracle quarterly updates.
B28: 6 | C28: Retrofitting the Core HR and Security suites onto the uplifted framework.
B29: 7 | C29: Automation of ORC configuration/setup itself (Setup and Maintenance tasks).
B31: RISKS
C32: Risk | D32: Impact if it materialises | E32: Mitigation
C33: Test scripts are not yet baselined — the register flags steps, data and expected results as still to be reviewed. | D33: Rework of built scripts; the largest single threat to the estimate. | E33: Gate the build on a signed-off script; sequence modules so stable ones are automated first.
C34: All locator maintenance sits with the team — no vendor absorbs Oracle UI change. | D34: Suite decays across the four Oracle quarterly updates a year if maintenance is unfunded. | E34: Fund a maintenance retainer at handover; run against each Oracle update preview environment; keep locators centralised in page objects.
C35: Component library is the critical path — scripting cannot start on a module until its page objects exist. | D35: Adding testers early produces idle capacity or duplicated locators. | E35: One senior engineer owns the library; stagger module starts as the phase plan shows.
C36: Key-person dependency on the engineers who built the existing framework. | D36: Reuse assumptions collapse; effort trends back toward a from-scratch build. | E36: Book handover time explicitly; document the locator convention and wrapper API before build starts.
C37: redwoodSync() currently uses a fixed 4-second sleep, and a browser is launched per scenario. | D37: Dry run and every later regression cycle run far slower than they need to. | E37: Included in the 32-hour uplift: condition-based waits, ThreadLocal driver, session reuse.
C38: Third-party integration sandboxes (Talview, Mercer Belong, PeopleSoft, background check) may be unavailable. | D38: 9 Complex scripts cannot be automated end to end; coverage drops. | E38: Confirm sandbox availability before build; otherwise stub the boundary and assert only ORC-side behaviour.
C39: Test users and role provisioning delayed across the recruiting personas. | D39: Blocks build and dry run — most scripts need two or more personas. | E39: Raise provisioning as a week-1 dependency with named owners.
